{
  "app": {
    "[project]/src/app/auth/page": [
      "static/media/83afe278b6a6bb3c-s.p.3a6ba036.woff2",
      "static/media/de161955856a921d-s.p.25da2b95.woff2",
      "static/media/0c8c4ded07fff55c-s.p.5c4452a7.woff2",
      "static/media/0c89a48fa5027cee-s.p.4564287c.woff2"
    ],
    "[project]/src/app/dashboard/meta/page": [
      "static/media/83afe278b6a6bb3c-s.p.3a6ba036.woff2",
      "static/media/de161955856a921d-s.p.25da2b95.woff2",
      "static/media/0c8c4ded07fff55c-s.p.5c4452a7.woff2",
      "static/media/0c89a48fa5027cee-s.p.4564287c.woff2"
    ],
    "[project]/src/app/dashboard/skippy/page": [
      "static/media/83afe278b6a6bb3c-s.p.3a6ba036.woff2",
      "static/media/de161955856a921d-s.p.25da2b95.woff2",
      "static/media/0c8c4ded07fff55c-s.p.5c4452a7.woff2",
      "static/media/0c89a48fa5027cee-s.p.4564287c.woff2"
    ],
    "[project]/src/app/dashboard/snooks/page": [
      "static/media/83afe278b6a6bb3c-s.p.3a6ba036.woff2",
      "static/media/de161955856a921d-s.p.25da2b95.woff2",
      "static/media/0c8c4ded07fff55c-s.p.5c4452a7.woff2",
      "static/media/0c89a48fa5027cee-s.p.4564287c.woff2"
    ],
    "[project]/src/app/page": [
      "static/media/83afe278b6a6bb3c-s.p.3a6ba036.woff2",
      "static/media/de161955856a921d-s.p.25da2b95.woff2",
      "static/media/0c8c4ded07fff55c-s.p.5c4452a7.woff2",
      "static/media/0c89a48fa5027cee-s.p.4564287c.woff2"
    ]
  },
  "appUsingSizeAdjust": true,
  "pages": {},
  "pagesUsingSizeAdjust": false
}